cvtools/__init__.py
cvtools/cv_load_image.py
cvtools-0.0.2.dist-info/DESCRIPTION.rst
cvtools-0.0.2.dist-info/METADATA
cvtools-0.0.2.dist-info/RECORD
cvtools-0.0.2.dist-info/WHEEL
cvtools-0.0.2.dist-info/metadata.json
cvtools-0.0.2.dist-info/top_level.txt
