Metadata-Version: 2.0
Name: cvtools
Version: 0.0.2
Summary: OpenCV tools for CV applications
Home-page: https://github.com/samson-wang/cvtools.git
Author: Samson Wang
Author-email: samson.c.wang@gmail.com
License: UNKNOWN
Keywords: opencv,image,http
Platform: UNKNOWN
